{
    "@class": "com.kony.gen.viz.model.component.KVizImage2",
    "DNDConfig": null,
    "__parentReadjusting__": false,
    "_base64_": null,
    "_height_": {
        "type": "string",
        "value": "40dp"
    },
    "_left_": {
        "type": "string",
        "value": "0dp"
    },
    "_margin_": [
        0,
        0,
        0,
        0
    ],
    "_padding_": [
        0,
        0,
        0,
        0
    ],
    "_skin_": "s319dbfc5808408bbf0cda0a09d985ce",
    "_src_": "swipe_ap.png",
    "_top_": {
        "type": "string",
        "value": "0dp"
    },
    "_width_": {
        "type": "string",
        "value": "20dp"
    },
    "canUpdateUI": true,
    "containerweight": 100,
    "context": {
        "channel": "mobile",
        "formID": "frmLoginKA",
        "ispercent": true,
        "platform": "iphone",
        "templateType": "forms",
        "topLevelBox": null
    },
    "enabled": false,
    "id": "swipeIcon",
    "imagescalemode": 1,
    "info": null,
    "invokedProperty": "src",
    "ispercent": true,
    "isvisible": false,
    "kuid": "bc1784fae1d54ce4b8c4382d487574f7",
    "name": "kony.ui.Image2",
    "parent": "accountPreviewIndicator",
    "pf": "frmLoginKA",
    "srcType": 1,
    "wType": "Image",
    "widgetalignment": 5,
    "zindex": 1
}