{
    "@class": "com.kony.gen.viz.model.component.KVizLabel",
    "DNDConfig": null,
    "__parentReadjusting__": false,
    "_height_": {
        "type": "ref",
        "value": "preferred"
    },
    "_left_": {
        "type": "string",
        "value": "5%"
    },
    "_margin_": [
        1,
        1,
        1,
        1
    ],
    "_padding_": [
        0,
        0,
        0,
        0
    ],
    "_skin_": "seb0b5ab7d5c4818843c1cbeba2ae2d4",
    "_text_": "Label",
    "_width_": {
        "type": "ref",
        "value": "preferred"
    },
    "_wrapping_": 2,
    "canUpdateUI": true,
    "centery": {
        "type": "string",
        "value": "50%"
    },
    "containerId": true,
    "containerweight": 100,
    "contentalignment": 4,
    "enabled": false,
    "id": "contactListLabel",
    "info": null,
    "ipad": {
        "psp": {
            "wrapping": 2
        }
    },
    "iphone": {
        "psp": {
            "wrapping": 2
        }
    },
    "isvisible": true,
    "kuid": "5841ac1b117d4dbeb7c7b498c76ca2d2",
    "name": "kony.ui.Label",
    "parent": "CopyFBox065c77100453543",
    "pf": "CopyFBox065c77100453543",
    "tooltip": "",
    "wType": "Label",
    "zindex": 1
}