{
    "@class": "com.kony.gen.viz.model.component.KVizImage2",
    "DNDConfig": null,
    "__parentReadjusting__": false,
    "_base64_": null,
    "_height_": {
        "type": "string",
        "value": "115%"
    },
    "_left_": {
        "type": "string",
        "value": "0dp"
    },
    "_margin_": [
        0,
        0,
        0,
        0
    ],
    "_padding_": [
        0,
        0,
        0,
        0
    ],
    "_render_": true,
    "_skin_": "sa625024fef740fea5133ed43bbfac5f",
    "_src_": "tranfer_new_bg.png",
    "_top_": {
        "type": "string",
        "value": "-20dp"
    },
    "_width_": {
        "type": "string",
        "value": "137.33%"
    },
    "android": {
        "render": true
    },
    "androidwearos": {
        "render": false
    },
    "canUpdateUI": true,
    "centerx": {
        "type": "string",
        "value": "50%"
    },
    "containerweight": 100,
    "context": {
        "channel": "mobile",
        "formID": "frmAccountDetailKA",
        "ispercent": true,
        "platform": "spaip",
        "templateType": "forms",
        "topLevelBox": null
    },
    "id": "bgImage",
    "imagescalemode": 1,
    "info": null,
    "invokedProperty": "src",
    "iphone": {
        "render": true
    },
    "isvisible": true,
    "kuid": "f19c3892031946abb657eb9aa8d0e70b",
    "name": "kony.ui.Image2",
    "parent": "accountsBG",
    "pf": "frmAccountDetailKA",
    "spaan": {
        "render": false
    },
    "spabb": {
        "render": false
    },
    "spaip": {
        "render": false
    },
    "spawinphone8": {
        "render": false
    },
    "srcType": 1,
    "wType": "Image",
    "widgetalignment": 5,
    "winphone8": {
        "render": true
    },
    "zindex": 1
}