{
    "@class": "com.kony.gen.viz.model.component.KVizButton",
    "DNDConfig": null,
    "__parentReadjusting__": false,
    "_height_": {
        "type": "string",
        "value": "100%"
    },
    "_margin_": [
        6,
        6,
        6,
        6
    ],
    "_padding_": [
        0,
        0,
        0,
        0
    ],
    "_right_": {
        "type": "string",
        "value": "0.00%"
    },
    "_skin_": "s1a96e0a6f17402ca691f55c7b41e893",
    "_text_": "Sign Out",
    "_top_": {
        "type": "string",
        "value": "0dp"
    },
    "_width_": {
        "type": "string",
        "value": "90dp"
    },
    "canUpdateUI": true,
    "containerweight": 100,
    "contentalignment": 5,
    "displaytext": true,
    "focusskin": "s55cab51ac7b40b5a2db38b7b9c5822a",
    "id": "signOutButton",
    "ide_onClick": "AS_Button_002a701951a9426b8c25f8dcdb9bb591",
    "info": null,
    "iphone": {
        "psp": {
            "showProgressIndicator": false
        }
    },
    "isvisible": true,
    "kuid": "ba161df9400544f2aa2cb4e0871448b9",
    "name": "kony.ui.Button",
    "onclick": "AS_Button_002a701951a9426b8c25f8dcdb9bb591",
    "parent": "iosTitleBar",
    "pf": "frmUserSettingsKA",
    "showprogressindicator": false,
    "texti18n": "i18n.more.frmMoreLandingKA.signOutButton",
    "wType": "Button",
    "zindex": 10
}