{
    "@class": "com.kony.gen.viz.model.component.KVizLabel",
    "DNDConfig": null,
    "__parentReadjusting__": false,
    "_height_": {
        "type": "ref",
        "value": "preferred"
    },
    "_margin_": [
        1,
        1,
        1,
        1
    ],
    "_padding_": [
        0,
        0,
        0,
        0
    ],
    "_skin_": "s081a9429ae54fd889bc06aa3a05a4a2",
    "_text_": "-$56.00",
    "_top_": {
        "type": "string",
        "value": "30dp"
    },
    "_width_": {
        "type": "string",
        "value": "80%"
    },
    "_wrapping_": 2,
    "canUpdateUI": true,
    "centerx": {
        "type": "string",
        "value": "50%"
    },
    "containerweight": 100,
    "contentalignment": 5,
    "enabled": false,
    "id": "lblTransactionAmountKA",
    "info": null,
    "ipad": {
        "psp": {
            "wrapping": 2
        }
    },
    "iphone": {
        "psp": {
            "wrapping": 2
        }
    },
    "isvisible": true,
    "kuid": "611fcb2bda394357998b59f34ef2f1d4",
    "name": "kony.ui.Label",
    "parent": "flxBillInfoKA",
    "pf": "frmBillDetailsKA",
    "texti18n": "i18n.transfer.frmBillDetailsKA.lblTransactionAmountKA",
    "tooltip": "",
    "wType": "Label"
}