{
    "AS_Button_090d523b438b4da2ae190d0b439736d4": {
        "id": "AS_Button_090d523b438b4da2ae190d0b439736d4",
        "type": "ACTION_SEQUENCE",
        "params": [{
            "datatype": "collection",
            "name": "eventobject"
        }],
        "language": "js",
        "actions": [{
            "id": "NAVIGATE_TO_FORM___1bc5462ec74540c691c7023585aa3657",
            "type": "NAVIGATE_TO_FORM",
            "formId": "frmMoreLandingKA",
            "formKUID": "f90cf53e47ae407c83e2e30720fff3da",
            "mappings": {},
            "mappingsOrder": [],
            "parentId": "",
            "callbackType": null,
            "enableMappingEditor": true
        }]
    }
}