{
    "AS_TextField_d53b58c2166349ceb5d23f435433bb9d": {
        "id": "AS_TextField_d53b58c2166349ceb5d23f435433bb9d",
        "type": "ACTION_SEQUENCE",
        "params": [{
            "datatype": "collection",
            "name": "eventobject"
        }, {
            "datatype": "string",
            "name": "changedtext"
        }],
        "contextObj": {
            "name": "frmLoginKA",
            "type": "forms",
            "platform": "",
            "KUID": "7b1aa8fceb6b4070833e9eab879b0e5e"
        },
        "language": "js",
        "actions": [{
            "id": "ADD_SNIPPET_ide_onDone_b8f73e28c8424705bb0f0e8a45fdcf77",
            "type": "ADD_SNIPPET",
            "codeSnippet": "loginKeyboardInactive();",
            "callbackType": null
        }]
    }
}